lasp/__init__.py
lasp/lasp_cache.py
lasp/lasp_fuse.py
lasp/lasp_fuse_parallel.py
lasp/lasp_naive.py
lasp/lightning_attention.py
lasp/version.py
lasp/utils/__init__.py
lasp/utils/module_utils.py
lasp/utils/seq_parallel_manager.py
lasp-0.0.1.dist-info/LICENSE
lasp-0.0.1.dist-info/METADATA
lasp-0.0.1.dist-info/WHEEL
lasp-0.0.1.dist-info/top_level.txt
lasp-0.0.1.dist-info/RECORD
